wedo2py_rpi5-1.0.1.dist-info/licenses/LICENCE
wedo2python/ __init__.py
wedo2python/app.py
wedo2py_rpi5-1.0.1.dist-info/METADATA
wedo2py_rpi5-1.0.1.dist-info/WHEEL
wedo2py_rpi5-1.0.1.dist-info/top_level.txt
wedo2py_rpi5-1.0.1.dist-info/RECORD
