Metadata-Version: 2.4
Name: wedo2py-rpi5
Version: 1.0.1
Summary: LEGO WeDo 2.0 BLE control library for Raspberry Pi using Bleak
Author-email: Evangelia Anastasaki <eveanast@gmail.com>
Project-URL: Homepage, https://github.com/eveanast/wedo2py-rpi5
Project-URL: Repository, https://github.com/eveanast/wedo2py-rpi5
Project-URL: Issues, https://github.com/eveanast/wedo2py-rpi5/issues
Project-URL: Documentation, https://github.com/eveanast/wedo2py-rpi5#readme
Classifier: Development Status :: 5 - Production/Stable
Classifier: Intended Audience :: Education
Classifier: Intended Audience :: Developers
Classifier: License :: OSI Approved :: Apache Software License
Classifier: Programming Language :: Python
Classifier: Programming Language :: Python :: 3
Classifier: Programming Language :: Python :: 3.9
Classifier: Programming Language :: Python :: 3.10
Classifier: Programming Language :: Python :: 3.11
Classifier: Operating System :: POSIX :: Linux
Classifier: Topic :: Education
Classifier: Topic :: Software Development :: Libraries :: Python Modules
Requires-Python: >=3.9
License-File: LICENCE
Requires-Dist: bleak>=0.21
Dynamic: license-file
